Workbook

Sheet 1 Inicio
B2: UNIDAD 2 — TRANSACCIONES DE CAPITAL
B3: Contabilidad Financiera · Sección 2 · ESEN · Trimestre 3/2026
B4: Profesora Antonia Caballero de Siman
B6: Nombre del estudiante:
B7: Carnet:
B8: Fecha de entrega:
B10: CÓDIGO DE HONOR
B11: "Por mi honor y ante mis compañeros, me comprometo a que esta actividad académica refleje mi verdadero nivel de conocimientos, evitando realizar cualquier forma de deshonestidad académica (por ejemplo, copiar o plagiar)."
B15: GUÍA DE HOJAS DE ESTE LIBRO
B16: 2 Marco Normativo | C16: Artículos y cifras oficiales del tema, tomadas del PDF de la clase.
B17: 3 Cálculo Emisión | C17: Ejercicio 1 de la guía (XYZ, S.A. de C.V.) resuelto con fórmulas.
B18: 4 Cálculo Práctica | C18: Misma estructura, en blanco, para practicar con datos nuevos.
B19: 5 Asientos Resueltos | C19: Libro diario de la emisión y de dividendos preferentes, enlazado a la Hoja 3.
B20: 6 Asientos Práctica | C20: Plantilla en blanco del libro diario.
B21: 7 Producto Final | C21: Sección de Patrimonio del Balance General, resuelta.
B22: 8 Producto Final Práct. | C22: Plantilla en blanco de la misma sección.
B24: LEYENDA DE COLORES
C25: Fila de cuenta de Activo
C26: Fila de cuenta de Pasivo
C27: Fila de cuenta de Patrimonio
C28: Marco legal / cifra normativa
C29: Celda para completar (práctica)
C30: Nota o instrucción pedagógica
B31: Texto azul | C31: valor de entrada que puedes cambiar
B32: Texto negro | C32: fórmula o cálculo automático (no editar)
B33: Texto gris | C33: nota o instrucción

Sheet 2 Marco Normativo
B2: MARCO NORMATIVO — UNIDAD 2: TRANSACCIONES DE CAPITAL
B3: Fuente: Unidad 2 Transacciones de capital.pdf + Acciones de Tesorería.pdf (clase del 1-3 de septiembre de 2026). El PDF no cita números de artículo del Código de Comercio para esta unidad; se referencia en términos generales.
B5: Constitución de la Sociedad Anónima
B6: Capital social mínimo | C6: USD $2,000 | E6: Código de Comercio de El Salvador
B7: Mínimo pagado a la inscripción | C7: 5% del capital social | E7: Código de Comercio de El Salvador
B8: Plazo para pagar el resto | C8: Dentro del año siguiente a la inscripción | E8: Código de Comercio de El Salvador
B9: Número mínimo de accionistas | C9: 2 (sin máximo) | E9: Código de Comercio de El Salvador
B11: Acciones comunes y preferentes
B12: Valor nominal mínimo de una acción | C12: $1 o múltiplos enteros de uno | E12: Código de Comercio de El Salvador
B13: Prohibición de venta bajo valor nominal | C13: Aplica a toda emisión | E13: Código de Comercio de El Salvador
B14: Acciones deben ser | C14: Nominativas | E14: Código de Comercio de El Salvador
B15: Dividendo mínimo de acciones preferentes | C15: 6% del valor nominal | E15: Código de Comercio de El Salvador
B16: Acciones preferentes recuperan voto pleno si | C16: No se les paga dividendo por más de 3 ejercicios (no necesariamente consecutivos) | E16: Código de Comercio de El Salvador
B18: Dividendos — Impuesto sobre la Renta
B19: Retención de ISR sobre dividendos pagados | C19: 5% | E19: Ley del Impuesto sobre la Renta
B20: Si no se retiene | C20: El contribuyente liquida el impuesto por separado de otras rentas | E20: Ley del Impuesto sobre la Renta
B22: Acciones de tesorería (referencia contable, no legal)
B23: Registro | C23: Al costo de recompra, nunca al valor nominal | E23: Acciones de Tesorería.pdf
B24: Reporte en el Balance General | C24: Debajo de Utilidades Retenidas, como reducción del Patrimonio | E24: Acciones de Tesorería.pdf
B25: Acciones en circulación | C25: acciones emitidas menos acciones en tesorería | E25: Acciones de Tesorería.pdf

Sheet 3 Calculo Emision
B2: CÁLCULO — EMISIÓN DE ACCIONES (Ejercicio 1, guía de la profesora)
B3: XYZ, S.A. de C.V. — emisión del 1 de enero de 2024, pagada totalmente en efectivo.
B5: Tipo de acción | C5: Cantidad | D5: Valor Nominal | E5: Valor de Mercado | F5: Capital a Valor Nominal | G5: Prima (cap. pagado en exceso) | H5: ¿Por qué?
B6: Preferente | C6: 1000 | D6: 50 | E6: 60 | F6: =C6*D6 -> 50000 | G6: =C6*(E6-D6) -> 10000 | H6: Capital a VN = cantidad × valor nominal. Prima = cantidad × (valor de mercado − valor nominal): nunca es utilidad.
B7: Común | C7: 10000 | D7: 100 | E7: 120 | F7: =C7*D7 -> 1000000 | G7: =C7*(E7-D7) -> 200000 | H7: Misma lógica que la fila anterior, para la clase de acciones comunes.
B8: Total emisión | F8: =SUM(F6:F7) -> 1050000 | G8: =SUM(G6:G7) -> 210000
B9: Total capital social emitido (= efectivo recibido) | F9: =F8+G8 -> 1260000
B12: Información previa a la emisión (31 de diciembre de 2023) — para la Hoja 7
B13: Utilidades retenidas previas | D13: 200000
B14: Acciones comunes previas en circulación | C14: 12000 | D14: =C14*D7 -> 1200000 | E14: Capital común previo = acciones previas × VN de la acción común (misma VN que la emisión nueva)

Sheet 4 Calculo Practica
B2: CÁLCULO — EMISIÓN DE ACCIONES (práctica)
B3: Ceiba Andina, S.A. de C.V. emite acciones el 1 de abril de 2026, pagadas totalmente en efectivo. Completa las celdas en rosa con la misma lógica de la Hoja 3.
B5: Tipo de acción | C5: Cantidad | D5: Valor Nominal | E5: Valor de Mercado | F5: Capital a Valor Nominal | G5: Prima (cap. pagado en exceso) | H5: ¿Por qué?
B6: Preferente | C6: 2500 | D6: 40 | E6: 47 | H6: Escribe aquí tu fórmula: cantidad × VN
B7: Común | C7: 15000 | D7: 15 | E7: 19 | H7: Escribe aquí tu fórmula: cantidad × (VM − VN)
B8: Total emisión
B9: Total capital social emitido (= efectivo recibido)
B12: Información previa a la emisión — para la Hoja 8
B13: Utilidades retenidas previas | D13: 60000
B14: Acciones comunes previas en circulación | C14: 9000 | E14: Calcula: acciones previas × VN de la acción común

Sheet 5 Asientos Resueltos
B2: LIBRO DIARIO — ASIENTOS RESUELTOS
B4: Partida 1 — Emisión de acciones (XYZ, S.A. de C.V., enlazada a la Hoja 3)
B5: Fecha | C5: Cuenta | D5: Clasif. | E5: Debe | F5: Haber
B6: 01-ene-24 | C6: Efectivo | D6: Activo | E6: ='3 Calculo Emision'!F9 -> 1260000
C7: Capital preferente | D7: Patrimonio | F7: ='3 Calculo Emision'!F6 -> 50000
C8: Capital pagado en exceso: preferente | D8: Patrimonio | F8: ='3 Calculo Emision'!G6 -> 10000
C9: Capital común | D9: Patrimonio | F9: ='3 Calculo Emision'!F7 -> 1000000
C10: Capital pagado en exceso: común | D10: Patrimonio | F10: ='3 Calculo Emision'!G7 -> 200000
C11: Emisión de acciones preferentes y comunes con prima, pagada en efectivo
B14: Partida 2 — Declaración y pago de dividendos preferentes (DEF, S.A. de C.V., diapositiva 31)
B15: Acciones preferentes en circulación | C15: 2000
B16: Valor nominal | C16: 50
B17: % de dividendo preferente | C17: 0.06
B18: % de retención ISR sobre dividendos | C18: 0.05
B19: Dividendo total declarado | C19: =C15*C16*C17 -> 6000
B21: Fecha | C21: Cuenta | D21: Clasif. | E21: Debe | F21: Haber
B22: 01-may | C22: Utilidades retenidas | D22: Patrimonio | E22: =C19 -> 6000
C23: Dividendos por pagar | D23: Pasivo | F23: =C19 -> 6000
C24: Declaración de dividendo preferente en efectivo
B26: 30-may | C26: Dividendos por pagar | D26: Pasivo | E26: =C19 -> 6000
C27: Retenciones por pagar ISR (5%) | D27: Pasivo | F27: =C19*C18 -> 300
C28: Efectivo | D28: Activo | F28: =C19-F27 -> 5700
C29: Pago del dividendo preferente, neto de la retención de ISR

Sheet 6 Asientos Practica
B2: LIBRO DIARIO — ASIENTOS (práctica)
B4: Partida 1 — Emisión de acciones (usa tus resultados de la Hoja 4)
B5: Fecha | C5: Cuenta | D5: Clasif. | E5: Debe | F5: Haber
B6: 01-abr-26 | C6: Efectivo
C7: Capital preferente
C8: Capital pagado en exceso: preferente
C9: Capital común
C10: Capital pagado en exceso: común
C11: Escribe aquí el concepto de la partida
B14: Partida 2 — Declaración y pago de dividendos preferentes (elige tus propios datos)
B15: Acciones preferentes en circulación
B16: Valor nominal
B17: % de dividendo preferente (Hoja 2, Marco Normativo)
B18: % de retención ISR (Hoja 2, Marco Normativo)
B19: Dividendo total declarado
B21: Fecha | C21: Cuenta | D21: Clasif. | E21: Debe | F21: Haber
C22: Utilidades retenidas
C23: Dividendos por pagar
C25: Dividendos por pagar
C26: Retenciones por pagar ISR
C27: Efectivo

Sheet 7 Producto Final
B2: PRODUCTO FINAL — SECCIÓN DE PATRIMONIO DEL BALANCE GENERAL
B3: XYZ, S.A. de C.V. — al 31 de enero de 2024 (después de la emisión de la Hoja 3)
B5: Patrimonio o Capital Contable
B6: Capital preferente: valor nominal $50; 1,000 acciones | C6: ='3 Calculo Emision'!F6 -> 50000
B7: Capital pagado en exceso del valor nominal: preferente | C7: ='3 Calculo Emision'!G6 -> 10000
B8: Capital común: valor nominal $100; 22,000 acciones emitidas | C8: ='3 Calculo Emision'!D14+'3 Calculo Emision'!F7 -> 2200000
B9: Capital pagado en exceso del valor nominal: común | C9: ='3 Calculo Emision'!G7 -> 200000
B10: Capital social pagado (subtotal) | C10: =SUM(C6:C9) -> 2460000
B11: Utilidades Retenidas | C11: ='3 Calculo Emision'!D13 -> 200000
B12: Patrimonio o Capital Contable total | C12: =C10+C11 -> 2660000

Sheet 8 Producto Final Practica
B2: PRODUCTO FINAL — SECCIÓN DE PATRIMONIO (práctica)
B3: Ceiba Andina, S.A. de C.V. — completa con tus resultados de la Hoja 4
B5: Patrimonio o Capital Contable
B6: Capital preferente: valor nominal, cantidad de acciones
B7: Capital pagado en exceso del valor nominal: preferente
B8: Capital común: valor nominal, cantidad de acciones totales
B9: Capital pagado en exceso del valor nominal: común
B10: Capital social pagado (subtotal)
B11: Utilidades Retenidas
B12: Patrimonio o Capital Contable total
